picocache/__init__.py
picocache/base.py
picocache/django.py
picocache/redis.py
picocache/sqlalchemy.py
picocache/sqlite.py
picocache/utils.py
picocache-1.3.0.dist-info/licenses/LICENSE
picocache-1.3.0.dist-info/WHEEL
picocache-1.3.0.dist-info/METADATA
picocache-1.3.0.dist-info/RECORD
