Metadata-Version: 2.4
Name: picocache
Version: 1.3.0
Summary: persistent decorators mirroring functools.lru_cache
Requires-Python: >=3.11
License-File: LICENSE
Requires-Dist: django>=5.0.0 ; extra == "django"
Requires-Dist: redis>=5.2.1 ; extra == "redis"
Requires-Dist: sqlalchemy>=2.0.40 ; extra == "sqlalchemy"
Project-URL: Source, https://github.com/knowsuchagency/picocache
Provides-Extra: django
Provides-Extra: redis
Provides-Extra: sqlalchemy
